polars_permute-0.1.6.dist-info/METADATA
polars_permute-0.1.6.dist-info/WHEEL
polars_permute-0.1.6.dist-info/entry_points.txt
polars_permute-0.1.6.dist-info/licenses/LICENSE
polars_permute/__init__.py
polars_permute/py.typed
polars_permute-0.1.6.dist-info/RECORD
