Metadata-Version: 2.1
Name: polars-permute
Version: 0.1.6
Summary: A Polars plugin for easily reordering DataFrame columns
Author-Email: Louis Maddox <louismmx@gmail.com>
Classifier: Development Status :: 4 - Beta
Classifier: Intended Audience :: Developers
Classifier: Natural Language :: English
Classifier: License :: OSI Approved :: MIT License
Classifier: Operating System :: OS Independent
Classifier: Programming Language :: Python
Classifier: Programming Language :: Python :: Implementation :: CPython
Classifier: Programming Language :: Python :: 3
Classifier: Programming Language :: Python :: 3.10
Classifier: Programming Language :: Python :: 3.11
Classifier: Programming Language :: Python :: 3.12
Classifier: Programming Language :: Python :: 3.13
Classifier: Programming Language :: Python :: 3.14
Project-URL: Homepage, https://github.com/lmmx/polars-permute-plugin
Project-URL: Repository, https://github.com/lmmx/polars-permute-plugin.git
Requires-Python: >=3.10
Provides-Extra: polars
Requires-Dist: polars>=1.21.0; extra == "polars"
Provides-Extra: polars-lts-cpu
Requires-Dist: polars-lts-cpu>=1.21.0; extra == "polars-lts-cpu"
Provides-Extra: dev
Requires-Dist: pre-commit>=4.1.0; extra == "dev"
Requires-Dist: pytest>=8.3.4; extra == "dev"
Provides-Extra: natsort
Requires-Dist: natsort>=8.4.0; extra == "natsort"
